purple/Purple_methods.py
purple/__init__.py
purple_bio-0.4.2.5.dist-info/LICENSE
purple_bio-0.4.2.5.dist-info/METADATA
purple_bio-0.4.2.5.dist-info/WHEEL
purple_bio-0.4.2.5.dist-info/top_level.txt
purple_bio-0.4.2.5.dist-info/RECORD
