Metadata-Version: 2.1
Name: purple-bio
Version: 0.4.2.5
Summary: Picking Unique Relevant Peptides for viraL Experiments
Home-page: https://gitlab.com/HartkopfF/Purple
Author: Johanna Lechner, Pauline Hiort and Felix Hartkopf
Author-email: lechnerJ@rki.de, hartkopff@rki.de
License: UNKNOWN
Platform: UNKNOWN
Classifier: Programming Language :: Python :: 3
Classifier: License :: OSI Approved :: GNU Lesser General Public License v3 or later (LGPLv3+)
Classifier: Operating System :: OS Independent
Requires-Dist: tqdm
Requires-Dist: biopython
Requires-Dist: pyyaml
